{"cameraMode":{"drawMode":0,"name":"Shaded","section":"Shading Mode"},"sceneLighting":true,"audioPlay":false,"sceneViewState":{"m_AlwaysRefresh":false,"showFog":true,"showSkybox":true,"showFlares":true,"showImageEffects":true,"showParticleSystems":true,"showVisualEffectGraphs":true,"m_FxEnabled":true},"in2DMode":false,"pivot":{"x":5.748385429382324,"y":0.4158288836479187,"z":-2.1068029403686525},"rotation":{"x":0.12488721311092377,"y":-0.6497965455055237,"z":0.10940279066562653,"w":0.7417715191841126},"size":3.437302827835083,"orthographic":false}